odoo/addons/survey_multiple_choice_max_answer/README.rst
odoo/addons/survey_multiple_choice_max_answer/__init__.py
odoo/addons/survey_multiple_choice_max_answer/__manifest__.py
odoo/addons/survey_multiple_choice_max_answer/i18n/it.po
odoo/addons/survey_multiple_choice_max_answer/i18n/survey_multiple_choice_max_answer.pot
odoo/addons/survey_multiple_choice_max_answer/models/__init__.py
odoo/addons/survey_multiple_choice_max_answer/models/survey_question.py
odoo/addons/survey_multiple_choice_max_answer/readme/CONTRIBUTORS.rst
odoo/addons/survey_multiple_choice_max_answer/readme/DESCRIPTION.rst
odoo/addons/survey_multiple_choice_max_answer/static/description/icon.png
odoo/addons/survey_multiple_choice_max_answer/static/description/index.html
odoo/addons/survey_multiple_choice_max_answer/tests/__init__.py
odoo/addons/survey_multiple_choice_max_answer/tests/test_survey_question.py
odoo/addons/survey_multiple_choice_max_answer/views/survey_question.xml
odoo14_addon_survey_multiple_choice_max_answer-14.0.1.0.1.dev7.dist-info/METADATA
odoo14_addon_survey_multiple_choice_max_answer-14.0.1.0.1.dev7.dist-info/WHEEL
odoo14_addon_survey_multiple_choice_max_answer-14.0.1.0.1.dev7.dist-info/top_level.txt
odoo14_addon_survey_multiple_choice_max_answer-14.0.1.0.1.dev7.dist-info/RECORD
